[
  {"parishId": null, "deaneryId": 1, "parishName": "KIAMUIRU"},
  {"parishId": null, "deaneryId": 1, "parishName": "CATHEDRAL"},
  {"parishId": null, "deaneryId": 1, "parishName": "RURINGU"},
  {"parishId": null, "deaneryId": 1, "parishName": "KING’ONG’O"},
  {"parishId": null, "deaneryId": 1, "parishName": "NGANGARITHI"},
  {"parishId": null, "deaneryId": 1, "parishName": "MWENJI"},

  {"parishId": null, "deaneryId": 2, "parishName": "ITHENGURI"},
  {"parishId": null, "deaneryId": 2, "parishName": "GIAKANJA"},
  {"parishId": null, "deaneryId": 2, "parishName": "WAMAGANA"},
  {"parishId": null, "deaneryId": 2, "parishName": "KARANGIA"},
  {"parishId": null, "deaneryId": 2, "parishName": "KIGOGOINI"},
  {"parishId": null, "deaneryId": 2, "parishName": "KANGAITA"},
  {"parishId": null, "deaneryId": 2, "parishName": "GITITU"},

  {"parishId": null, "deaneryId": 3, "parishName": "KARATINA"},
  {"parishId": null, "deaneryId": 3, "parishName": "MIIRI"},
  {"parishId": null, "deaneryId": 3, "parishName": "NGANDU"},
  {"parishId": null, "deaneryId": 3, "parishName": "KAMATU"},
  {"parishId": null, "deaneryId": 3, "parishName": "KABIRUINI"},
  {"parishId": null, "deaneryId": 3, "parishName": "KAHIRA INI"},
  {"parishId": null, "deaneryId": 3, "parishName": "GIKUMBO"},
  {"parishId": null, "deaneryId": 3, "parishName": "GATHUGU"},
  {"parishId": null, "deaneryId": 3, "parishName": "GIAKAIBEI"},

  {"parishId": null, "deaneryId": 4, "parishName": "MUKURWE INI"},
  {"parishId": null, "deaneryId": 4, "parishName": "GIKONDI"},
  {"parishId": null, "deaneryId": 4, "parishName": "KAHETI"},
  {"parishId": null, "deaneryId": 4, "parishName": "KIMONDO"},
  {"parishId": null, "deaneryId": 4, "parishName": "GIATHUGU"},

  {"parishId": null, "deaneryId": 5, "parishName": "DOLDOL"},
  {"parishId": null, "deaneryId": 5, "parishName": "ST THERESA EQUATOR"},
  {"parishId": null, "deaneryId": 5, "parishName": "CHRIST THE KING"},
  {"parishId": null, "deaneryId": 5, "parishName": "KALALU"},
  {"parishId": null, "deaneryId": 5, "parishName": "MATANYA"},

  {"parishId": null, "deaneryId": 6, "parishName": "CHAKA"},
  {"parishId": null, "deaneryId": 6, "parishName": "IRIGITHATHI"},
  {"parishId": null, "deaneryId": 6, "parishName": "MUNYU"},
  {"parishId": null, "deaneryId": 6, "parishName": "NARUMORU TOWN"},
  {"parishId": null, "deaneryId": 6, "parishName": "THEGU"},



  {"parishId": null, "deaneryId": 7, "parishName": "GATARAKWA"},
  {"parishId": null, "deaneryId": 7, "parishName": "ENDARASHA"},
  {"parishId": null, "deaneryId": 7, "parishName": "KAREMENO"},
  {"parishId": null, "deaneryId": 7, "parishName": "KAMARIKI"},
  {"parishId": null, "deaneryId": 7, "parishName": "WIYUMIRIRIE"},
  {"parishId": null, "deaneryId": 7, "parishName": "MUGUNDA"},
  {"parishId": null, "deaneryId": 7, "parishName": "SIRIMA"},
  {"parishId": null, "deaneryId": 7, "parishName": "MWEIGA"},

  {"parishId": null, "deaneryId": 8, "parishName": "BIRITHIA"},
  {"parishId": null, "deaneryId": 8, "parishName": "WITIMA"},
  {"parishId": null, "deaneryId": 8, "parishName": "KARIMA"},
  {"parishId": null, "deaneryId": 8, "parishName": "KARIKO"},
  {"parishId": null, "deaneryId": 8, "parishName": "KIGUMO"},
  {"parishId": null, "deaneryId": 8, "parishName": "KARUTHI"},
  {"parishId": null, "deaneryId": 8, "parishName": "OTHAYA"}
]
